{
  "livro": "Lamentações",
  "slug_livro": "lamentacoes",
  "testamento": "Antigo Testamento",
  "capitulo": 3,
  "total_versiculos": 66,
  "versiculos": [
    {
      "numero": 1,
      "texto": "Eu sou aquele homem que viu a aflição pela vara do seu furor."
    },
    {
      "numero": 2,
      "texto": "Ele me guiou e me fez andar em trevas e não na luz."
    },
    {
      "numero": 3,
      "texto": "Deveras fez virar e revirar a sua mão contra mim o dia todo."
    },
    {
      "numero": 4,
      "texto": "Fez envelhecer a minha carne e a minha pele, quebrou os meus ossos."
    },
    {
      "numero": 5,
      "texto": "Edificou contra mim, e me cercou de fel e trabalho."
    },
    {
      "numero": 6,
      "texto": "Assentou-me em lugares tenebrosos, como os que estavam mortos há muito."
    },
    {
      "numero": 7,
      "texto": "Cercou-me de uma sebe, e não posso sair; agravou os meus grilhões."
    },
    {
      "numero": 8,
      "texto": "Ainda quando clamo e grito, ele exclui a minha oração."
    },
    {
      "numero": 9,
      "texto": "Fechou os meus caminhos com pedras lavradas, fez tortuosas as minhas veredas."
    },
    {
      "numero": 10,
      "texto": "Fez-se-me como urso de emboscada, um leão em esconderijos."
    },
    {
      "numero": 11,
      "texto": "Desviou os meus caminhos, e fez-me em pedaços; deixou-me assolado."
    },
    {
      "numero": 12,
      "texto": "Armou o seu arco, e me pôs como alvo à flecha."
    },
    {
      "numero": 13,
      "texto": "Fez entrar nos meus rins as flechas da sua aljava."
    },
    {
      "numero": 14,
      "texto": "Fui feito um objeto de escárnio para todo o meu povo, e a sua canção todo o dia."
    },
    {
      "numero": 15,
      "texto": "Fartou-me de amarguras, embriagou-me de absinto."
    },
    {
      "numero": 16,
      "texto": "Quebrou com cascalho os meus dentes, abaixou-me na cinza."
    },
    {
      "numero": 17,
      "texto": "E afastaste da paz a minha alma; esqueci-me do bem."
    },
    {
      "numero": 18,
      "texto": "Então disse eu: Já pereceu a minha força, como também a minha esperança no Senhor."
    },
    {
      "numero": 19,
      "texto": "Lembra-te da minha aflição e do meu pranto, do absinto e do fel."
    },
    {
      "numero": 20,
      "texto": "Minha alma certamente disto se lembra, e se abate dentro de mim."
    },
    {
      "numero": 21,
      "texto": "Disto me recordarei na minha mente; por isso esperarei."
    },
    {
      "numero": 22,
      "texto": "As misericórdias do Senhor são a causa de não sermos consumidos, porque as suas misericórdias não têm fim;"
    },
    {
      "numero": 23,
      "texto": "Novas são cada manhã; grande é a tua fidelidade."
    },
    {
      "numero": 24,
      "texto": "A minha porção é o Senhor, diz a minha alma; portanto esperarei nele."
    },
    {
      "numero": 25,
      "texto": "Bom é o Senhor para os que esperam por ele, para a alma que o busca."
    },
    {
      "numero": 26,
      "texto": "Bom é ter esperança, e aguardar em silêncio a salvação do Senhor."
    },
    {
      "numero": 27,
      "texto": "Bom é para o homem suportar o jugo na sua mocidade."
    },
    {
      "numero": 28,
      "texto": "Assente-se solitário e fique em silêncio; porquanto Deus o pôs sobre ele."
    },
    {
      "numero": 29,
      "texto": "Ponha a sua boca no pó; talvez ainda haja esperança."
    },
    {
      "numero": 30,
      "texto": "Dê a sua face ao que o fere; farte-se de afronta."
    },
    {
      "numero": 31,
      "texto": "Pois o Senhor não rejeitará para sempre."
    },
    {
      "numero": 32,
      "texto": "Pois, ainda que entristeça a alguém, usará de compaixão, segundo a grandeza das suas misericórdias."
    },
    {
      "numero": 33,
      "texto": "Porque não aflige nem entristece de bom grado aos filhos dos homens."
    },
    {
      "numero": 34,
      "texto": "Pisar debaixo dos seus pés a todos os presos da terra,"
    },
    {
      "numero": 35,
      "texto": "Perverter o direito do homem perante a face do Altíssimo,"
    },
    {
      "numero": 36,
      "texto": "Subverter ao homem no seu pleito, não o veria o Senhor?"
    },
    {
      "numero": 37,
      "texto": "Quem é aquele que diz, e assim acontece, quando o Senhor o não mande?"
    },
    {
      "numero": 38,
      "texto": "Porventura da boca do Altíssimo não sai tanto o mal como o bem?"
    },
    {
      "numero": 39,
      "texto": "De que se queixa, pois, o homem vivente? Queixe-se cada um dos seus pecados."
    },
    {
      "numero": 40,
      "texto": "Esquadrinhemos os nossos caminhos, e provemo-los, e voltemos para o Senhor."
    },
    {
      "numero": 41,
      "texto": "Levantemos os nossos corações com as mãos para Deus nos céus, dizendo:"
    },
    {
      "numero": 42,
      "texto": "Nós transgredimos, e fomos rebeldes; por isso tu não perdoaste."
    },
    {
      "numero": 43,
      "texto": "Cobriste-te de ira, e nos perseguiste; mataste, não perdoaste."
    },
    {
      "numero": 44,
      "texto": "Cobriste-te de nuvens, para que não passe a nossa oração."
    },
    {
      "numero": 45,
      "texto": "Como escória e refugo nos puseste no meio dos povos."
    },
    {
      "numero": 46,
      "texto": "Todos os nossos inimigos abriram contra nós a sua boca."
    },
    {
      "numero": 47,
      "texto": "Temor e laço vieram sobre nós, assolação e destruição."
    },
    {
      "numero": 48,
      "texto": "Torrentes de água derramaram os meus olhos, por causa da destruição da filha do meu povo."
    },
    {
      "numero": 49,
      "texto": "Os meus olhos choram, e não cessam, porque não há descanso,"
    },
    {
      "numero": 50,
      "texto": "Até que o Senhor atente e veja desde os céus."
    },
    {
      "numero": 51,
      "texto": "Os meus olhos entristecem a minha alma, por causa de todas as filhas da minha cidade."
    },
    {
      "numero": 52,
      "texto": "Como ave me caçam os que, sem causa, são meus inimigos."
    },
    {
      "numero": 53,
      "texto": "Cortaram-me a vida na masmorra, e lançaram pedras sobre mim."
    },
    {
      "numero": 54,
      "texto": "águas correram sobre a minha cabeça; eu disse: Estou cortado."
    },
    {
      "numero": 55,
      "texto": "Invoquei o teu nome, Senhor, desde a mais profunda masmorra."
    },
    {
      "numero": 56,
      "texto": "Ouviste a minha voz; não escondas o teu ouvido ao meu suspiro, ao meu clamor."
    },
    {
      "numero": 57,
      "texto": "Tu te aproximaste no dia em que te invoquei; disseste: Não temas."
    },
    {
      "numero": 58,
      "texto": "Pleiteaste, Senhor, as causas da minha alma, remiste a minha vida."
    },
    {
      "numero": 59,
      "texto": "Viste, Senhor, a injustiça que me fizeram; julga a minha causa."
    },
    {
      "numero": 60,
      "texto": "Viste toda a sua vingança, todos os seus pensamentos contra mim."
    },
    {
      "numero": 61,
      "texto": "Ouviste a sua afronta, Senhor, todos os seus pensamentos contra mim,"
    },
    {
      "numero": 62,
      "texto": "Os lábios dos que se levantam contra mim e os seus desígnios me são contrários todo o dia."
    },
    {
      "numero": 63,
      "texto": "Observa-os ao assentarem-se e ao levantarem-se; eu sou a sua música."
    },
    {
      "numero": 64,
      "texto": "Tu lhes darás recompensa, Senhor, conforme a obra das suas mãos."
    },
    {
      "numero": 65,
      "texto": "Tu lhes darás ânsia de coração, maldição tua sobre eles."
    },
    {
      "numero": 66,
      "texto": "Na tua ira os perseguirás, e os destruirás de debaixo dos céus do Senhor."
    }
  ]
}